variatio/__init__.py
variatio/analyzer.py
variatio/data_validation.py
variatio/metrics.py
variatio/stat_significance.py
variatio/vizualizer.py
variatio-0.0.16.dist-info/METADATA
variatio-0.0.16.dist-info/WHEEL
variatio-0.0.16.dist-info/licenses/LICENSE
variatio-0.0.16.dist-info/RECORD
