Metadata-Version: 2.3
Name: variatio
Version: 0.0.16
Dynamic: Requires-Dist
Summary: An experimental Python library for advanced A/B testing analysis, leveraging statistical techniques and ML for deeper insights.
Project-URL: Homepage, https://github.com/dmitry-brazhenko/variatio
Project-URL: Documentation, https://github.com/dmitry-brazhenko/Variatio/blob/main/README.md
Project-URL: Repository, https://github.com/dmitry-brazhenko/variatio
Author-email: Dmitry Brazhenko <brazhenko.dmitry@gmail.com>
Maintainer-email: Dmitry Brazhenko <brazhenko.dmitry@gmail.com>
License: MIT License
License-File: LICENSE
Requires-Python: >=3.8
